atmos/__init__.py
atmos/constants.py
atmos/decorators.py
atmos/equations.py
atmos/plot.py
atmos/solve.py
atmos/tests.py
atmos/util.py
atmosp/__init__.py
atmosp/constants.py
atmosp/decorators.py
atmosp/equations.py
atmosp/plot.py
atmosp/solve.py
atmosp/tests.py
atmosp/util.py
src/__init__.py
src/constants.py
src/decorators.py
src/equations.py
src/plot.py
src/solve.py
src/tests.py
src/util.py
atmosp-0.2.9.dist-info/LICENSE.txt
atmosp-0.2.9.dist-info/METADATA
atmosp-0.2.9.dist-info/WHEEL
atmosp-0.2.9.dist-info/top_level.txt
atmosp-0.2.9.dist-info/RECORD
