Metadata-Version: 2.1
Name: atmosp
Version: 0.2.9
Summary: Atmospheric sciences utility library
Home-page: https://github.com/sunt05/atmosp
Author: Ting Sun
Author-email: sunting.05@gmail.com
License: MIT
Keywords: atmosp,atmospheric,equations,geoscience,science
Platform: UNKNOWN
Requires-Python: ~=3.6
Requires-Dist: six (>=1.9.0)
Requires-Dist: numexpr (>=2.3.0)
Requires-Dist: numpy (>=1.6)
Requires-Dist: nose (>=1.3)
Requires-Dist: setuptools (>=15.0)
Requires-Dist: pint (>=0.6)
Requires-Dist: unittest2 (>=1.0)
